pyshv-0.12.0.dist-info/licenses/LICENSE
shv/__init__.py
shv/__version__.py
shv/chainpack.py
shv/commonpack.py
shv/cpon.py
shv/path.py
shv/py.typed
shv/rpclogin.py
shv/rpcmessage.py
shv/rpcparam.py
shv/rpcri.py
shv/rpcurl.py
shv/shvversion.py
shv/value.py
shv/broker/__init__.py
shv/broker/__main__.py
shv/broker/broker.py
shv/broker/config.py
shv/broker/configabc.py
shv/broker/utils.py
shv/cpconv/__init__.py
shv/cpconv/__main__.py
shv/cpconv/cpconv.py
shv/rpcapi/__init__.py
shv/rpcapi/base.py
shv/rpcapi/client.py
shv/rpcapi/device.py
shv/rpcapi/methods.py
shv/rpcapi/valueclient.py
shv/rpcdef/__init__.py
shv/rpcdef/access.py
shv/rpcdef/alert.py
shv/rpcdef/dir.py
shv/rpcdef/errors.py
shv/rpcdef/file.py
shv/rpctransport/__canlog.py
shv/rpctransport/__init__.py
shv/rpctransport/abc.py
shv/rpctransport/can.py
shv/rpctransport/pipe.py
shv/rpctransport/stream.py
shv/rpctransport/tcp.py
shv/rpctransport/tty.py
shv/rpctransport/unix.py
shv/rpctransport/url.py
shv/rpctransport/ws.py
shv/rpctypes/__init__.py
shv/rpctypes/_tools.py
shv/rpctypes/any.py
shv/rpctypes/base.py
shv/rpctypes/bitfield.py
shv/rpctypes/blob.py
shv/rpctypes/bool.py
shv/rpctypes/datetime.py
shv/rpctypes/decimal.py
shv/rpctypes/double.py
shv/rpctypes/enum.py
shv/rpctypes/imap.py
shv/rpctypes/integer.py
shv/rpctypes/keystruct.py
shv/rpctypes/list.py
shv/rpctypes/map.py
shv/rpctypes/null.py
shv/rpctypes/oneof.py
shv/rpctypes/parse.py
shv/rpctypes/standard.py
shv/rpctypes/string.py
shv/rpctypes/struct.py
shv/rpctypes/tuple.py
shv/rpctypes/unsigned.py
pyshv-0.12.0.dist-info/METADATA
pyshv-0.12.0.dist-info/WHEEL
pyshv-0.12.0.dist-info/entry_points.txt
pyshv-0.12.0.dist-info/top_level.txt
pyshv-0.12.0.dist-info/RECORD
