Metadata-Version: 2.4
Name: pyshv
Version: 0.12.0
Summary: Pure Python SHV implementation
Author: Elektroline a.s.
License-Expression: MIT
Project-URL: Homepage, https://gitlab.com/silicon-heaven/pyshv
Project-URL: Bug Tracker, https://gitlab.com/silicon-heaven/pyshv/-/issues
Project-URL: Github, https://github.com/silicon-heaven/libshv-py
Classifier: Development Status :: 4 - Beta
Classifier: Programming Language :: Python :: 3
Classifier: Operating System :: OS Independent
Classifier: Framework :: AsyncIO
Classifier: Intended Audience :: Developers
Classifier: Topic :: Home Automation
Classifier: Topic :: System :: Networking
Classifier: Typing :: Typed
Requires-Python: >=3.11
License-File: LICENSE
Provides-Extra: websockets
Requires-Dist: websockets>=13.0; extra == "websockets"
Provides-Extra: canbus
Requires-Dist: python-can; extra == "canbus"
Provides-Extra: extra
Requires-Dist: asyncinotify; sys_platform == "linux" and extra == "extra"
Provides-Extra: test
Requires-Dist: pytest; extra == "test"
Requires-Dist: pytest-asyncio; extra == "test"
Requires-Dist: pytest-cov; extra == "test"
Provides-Extra: docs
Requires-Dist: sphinx; extra == "docs"
Requires-Dist: sphinx-book-theme; extra == "docs"
Requires-Dist: sphinx-mdinclude; extra == "docs"
Requires-Dist: sphinx-multiversion; extra == "docs"
Dynamic: license-file
